longpython/__init__.py
longpython/main.py
longpython/py.typed
longpython-0.1.1.dist-info/LICENSE
longpython-0.1.1.dist-info/METADATA
longpython-0.1.1.dist-info/WHEEL
longpython-0.1.1.dist-info/entry_points.txt
longpython-0.1.1.dist-info/RECORD
