Metadata-Version: 2.1
Name: longpython
Version: 0.1.1
Summary: CLI tool to print long python
Home-page: https://github.com/4513ECHO/longpython
License: MIT
Author: Hibiki(4513ECHO)
Author-email: mail@4513echo.dev
Requires-Python: >=3.9,<4.0
Classifier: License :: OSI Approved :: MIT License
Classifier: Programming Language :: Python
Classifier: Programming Language :: Python :: 3
Classifier: Programming Language :: Python :: 3.9
Classifier: Programming Language :: Python :: 3.10
Classifier: Programming Language :: Python :: 3.11
Classifier: Programming Language :: Python :: 3
Classifier: Programming Language :: Python :: 3 :: Only
Classifier: Programming Language :: Python :: 3.10
Classifier: Programming Language :: Python :: 3.9
Classifier: Programming Language :: Python :: Implementation :: CPython
Classifier: Typing :: Typed
Project-URL: Repository, https://github.com/4513ECHO/longpython
